[
	{
		"title": "Postcard",
		"url":"css-begginer/other/postcard/",
		"difficulty": "begginer",
		"technology": "css",
		"category": "other"
	},
	{
		"title": "One Page Portfolio",
		"url":"css-junior/bootstrap/one-page/",
		"technology": "css",
		"difficulty": "junior",
		"category": "bootstrap"
	},
	{
		"title": "Single Portfolio",
		"url":"css-junior/bootstrap/single-portfolio/",
		"technology": "css",
		"difficulty": "junior",
		"category": "bootstrap"
	},
	{
		"title": "Emoji",
		"url":"css-junior/drawing/emoji/",
		"category": "drawing",
		"technology": "css",
		"difficulty": "junior"
	},
	{
		"title": "Gameboy",
		"url":"css-junior/drawing/gameboy/",
		"category": "drawing",
		"technology": "css",
		"difficulty": "junior"
	},
	{
		"title": "Goku",
		"url":"css-junior/drawing/goku/",
		"category": "drawing",
		"technology": "css",
		"difficulty": "junior"
	},
	{
		"title": "First Parallax",
		"url":"css-junior/other/parallax/",
		"category": "other",
		"technology": "css",
		"difficulty": "junior"
	},
	{
		"title": "Planets",
		"url":"css-senior/animation/planets/",
		"category": "animation",
		"technology": "css",
		"difficulty": "senior"
	},
	{
		"title": "Solar System",
		"url":"css-senior/animation/solarsystem/",
		"category": "animation",
		"technology": "css",
		"difficulty": "senior"
	},
	{
		"title": "Second Parallax",
		"url":"css-senior/other/parallax/",
		"category": "other",
		"technology": "css",
		"difficulty": "senior"
	},
	{
		"title": "Timeline",
		"url":"css-senior/other/timeline/",
		"category": "other",
		"technology": "css",
		"difficulty": "senior"
	},
	{
		"title": "The Hangman Game",
		"url":"javascript-begginer/games/hangman/",
		"category": "games",
		"technology": "javascript",
		"difficulty": "begginer"
	},
	{
		"title": "Card Memory Game",
		"url":"javascript-begginer/games/memory/",
		"category": "games",
		"technology": "javascript",
		"difficulty": "begginer"
	},
	{
		"title": "Tic Tac Toe",
		"url":"javascript-begginer/games/tictactoe/",
		"category": "games",
		"technology": "javascript",
		"difficulty": "begginer"
	},
	{
		"title": "Simple Counter",
		"url":"javascript-begginer/other/counter/",
		"category": "other",
		"technology": "javascript",
		"difficulty": "begginer"
	},
	{
		"title": "Ultimate Excuse Generator",
		"url":"javascript-begginer/other/excuse-generator/",
		"category": "other",
		"technology": "javascript",
		"difficulty": "begginer"
	},
	{
		"title": "Minutes Cronometer",
		"url":"javascript-begginer/other/minutes-cronometer/",
		"category": "other",
		"technology": "javascript",
		"difficulty": "begginer"
	},
	{
		"title": "Random Card Generator",
		"url":"javascript-begginer/other/random-card/",
		"category": "other",
		"technology": "javascript",
		"difficulty": "begginer"
	},
	{
		"title": "Battlefield",
		"url":"javascript-junior/games/battlefield/",
		"category": "games",
		"technology": "javascript",
		"difficulty": "junior"
	},
	{
		"title": "Simple Calculator",
		"url":"javascript-junior/other/calculator/",
		"category": "other",
		"technology": "javascript",
		"difficulty": "junior"
	},
	{
		"title": "Deck Shuffler",
		"url":"javascript-junior/other/deck-shuffler/",
		"category": "other",
		"technology": "javascript",
		"difficulty": "junior"
	},
	{
		"title": "Classroom Timer",
		"url":"javascript-junior/other/timer/",
		"category": "other",
		"technology": "javascript",
		"difficulty": "junior"
	},
	{
		"title": "Nest Container Animation",
		"url":"jquery-begginer/animations/nestedcontainer/",
		"category": "animations",
		"technology": "jquery",
		"difficulty": "begginer"
	},
	{
		"title": "Traffic Light Animation",
		"url":"jquery-begginer/animations/trafficlight/",
		"category": "animations",
		"technology": "jquery",
		"difficulty": "begginer"
	},
	{
		"title": "Basic Portfolio",
		"url":"jquery-begginer/portfolios/basic/",
		"category": "portfolios",
		"technology": "jquery",
		"difficulty": "begginer"
	},
	{
		"title": "Instant Portfolio",
		"url":"jquery-begginer/portfolios/instant/",
		"category": "portfolios",
		"technology": "jquery",
		"difficulty": "begginer"
	},
	{
		"title": "My first php",
		"url":"jquery-begginer/portfolios/instant/",
		"category": "portfolios",
		"technology": "php",
		"difficulty": "begginer"
	}
]